COUNT.v
//--------------------------Project3----------------------------------------------------------------

module COUNT(A,B,C,mode,state,CountIn,CountOut);

	input A;
	input B;
	input C;
	input [1:0] mode;
	input [1:0] state;
	input [7:0] CountIn;
	output [7:0] CountOut;
	
	wire m0,m1,m2,m3;
	wire w0,w1,w2,w3;
	
	and (m0,A,~mode[0],~mode[1]);
	
	and (m1,A,B,mode[0],~mode[1]);
	
	xor (w0,A,B);
	and (m2,w0,~mode[0],mode[1]);
	
	xnor (w1,A,B,C);
	or (w2,A,B,C);
	and (m3,w1,w2,mode[0],mode[1]);
	
	xor (w3,state[0],state[1]);
	
	assign CountOut = (m0|m1|m2|m3)&w3 ? CountIn+7'd1 : CountIn;
	
endmodule

JUDGE.v
//--------------------------Project3----------------------------------------------------------------

module JUDGE(square_x,square_y,square_r,ans);
	
	input [7:0] square_x,square_y,square_r;				//central & radias
	output ans;					//Is target(x,y) in the circle or not?

	wire [7:0] diff_square;
	
	assign diff_square = square_r - square_x - square_y;
	assign ans = (diff_square[7]) ? 1'b0 : 1'b1;
	
endmodule

Multipiler.v
//--------------------------Project3----------------------------------------------------------------
//CO note - 2'nd multiplication algorithm
//0 <= A <= 7

module Multipiler(A,Product);
	
	input [3:0] A;
	output [7:0] Product;
	
	wire [7:0] temp0,temp1,temp2;
	
	assign temp0 = A[0] ? {A,A}>>1:{4'd0,A}>>1;
	assign temp1 = temp0[0] ? (temp0+{A,4'd0})>>1:temp0>>1;
	assign temp2 = temp1[0] ? (temp1+{A,4'd0})>>1:temp1>>1;
	assign Product = temp2[0] ? (temp2+{A,4'd0})>>1:temp2>>1;
	
endmodule

Subtractor.v
module Subtractor(A,B,diff);
	input [3:0] A;
	input [3:0] B;
	output [3:0] diff;
	
	assign diff = A+(~B)+4'd1;

endmodule

CONTROL.v
module CONTROL(cs,target_cs,en,ns,target_ns,valid,busy);
	input [1:0] cs;	
	input [7:0] target_cs;
	input en;
	output reg [1:0] ns;
	output reg [7:0] target_ns;
	output valid;
	output busy;
	
	//state0: initialize ; state1: get value ; state2: calculate ; state3: valid candidate
	always@(*) begin
		case(cs)
			2'd0: 
			begin
				ns = (en) ? 2'd1:2'd0;
				target_ns = (en) ? (target_cs[3:0] & 4'b1000) ? target_cs+8'h09:target_cs+8'h01 : 8'h11;
			end
			2'd1: 
			begin
				ns = (target_cs!=8'h87) ? 2'd1:2'd2;
				target_ns = (target_cs[3:0] & 4'b1000) ? target_cs+8'h09 : target_cs+8'h01;
			end
			2'd2: 
			begin
				ns = 2'd3;
				target_ns = target_cs;
			end
			2'd3: 
			begin
				ns = 2'd0;
				target_ns = 8'h10;
			end
		endcase
	end
	
	assign valid = (cs==2'd3) ? 1'b1:1'b0;
	assign busy = (cs!=2'd0) ? 1'b1:1'b0; 
	
endmodule

SET.v
//--------------------------Project3----------------------------------------------------------------

`include "JUDGE.v"
`include "Multipiler.v"
`include "COUNT.v"
`include "CONTROL.v" 

module SET ( clk , rst, en, central, radius, mode, busy, valid, candidate);

	input clk, rst;
	input en;
	input [23:0] central;
	input [11:0] radius;
	input [1:0] mode;
	output busy;
	output valid;
	output [7:0] candidate;
	
	reg [1:0] cs;		
	reg [1:0] ns;
	reg [7:0] target_ns;
	reg [7:0] target_cs;	
	reg [7:0] CountIn;
	wire ans_A,ans_B,ans_C;
	wire [3:0] xdiff_A,xdiff_B,xdiff_C;
	wire [3:0] ydiff_A,ydiff_B,ydiff_C;
	wire [7:0] Prod_rA,Prod_rB,Prod_rC;		
	wire [7:0] Prod_xdA,Prod_xdB,Prod_xdC;
	wire [7:0] Prod_ydA,Prod_ydB,Prod_ydC;
	
	always@(posedge clk or posedge rst) begin
		if(rst) begin
			cs <= 2'd0;
			target_cs <= 8'h10;
			CountIn <= 8'd0;
		end
		else begin
			cs <= ns;
			target_cs <= target_ns;
			CountIn <= (cs==2'd3)?8'd0:candidate;
		end
	end 
	
	CONTROL CT(cs,target_cs,en,ns,target_ns,valid,busy);
	
	Subtractor S0(central[23:20],target_cs[7:4],xdiff_A);
	Subtractor S1(central[19:16],target_cs[3:0],ydiff_A);
	Subtractor S2(central[15:12],target_cs[7:4],xdiff_B);
	Subtractor S3(central[11:8],target_cs[3:0],ydiff_B);
	Subtractor S4(central[7:4],target_cs[7:4],xdiff_C);
	Subtractor S5(central[3:0],target_cs[3:0],ydiff_C);
	
	Multipiler M0(xdiff_A,Prod_xdA);
	Multipiler M1(ydiff_A,Prod_ydA);
	Multipiler M2(xdiff_B,Prod_xdB);
	Multipiler M3(ydiff_B,Prod_ydB);
	Multipiler M4(xdiff_C,Prod_xdC);
	Multipiler M5(ydiff_C,Prod_ydC);
	Multipiler M6(radius[11:8],Prod_rA);
	Multipiler M7(radius[7:4],Prod_rB);
	Multipiler M8(radius[3:0],Prod_rC);
	
	JUDGE JA(Prod_xdA,Prod_ydA,Prod_rA,ans_A);
	JUDGE JB(Prod_xdB,Prod_ydB,Prod_rB,ans_B);
	JUDGE JC(Prod_xdC,Prod_ydC,Prod_rC,ans_C);
	
	COUNT C0(ans_A,ans_B,ans_C,mode,cs,CountIn,candidate);
	
endmodule

testfixture.v
`timescale 1ns/10ps
`define SDFFILE    "SET_syn.sdf"    // Modify your sdf file name here
`define cycle 10.0
`define terminate_cycle 200000 // Modify your terminate ycle here
`include "/mnt3/CBDK_IC_Contest_v2.1/Verilog/tsmc13.v"
//`include "SET.v"

module testfixture1;

`define central_pattern "./dat/Central_pattern.dat"
`define radius_pattern "./dat/Radius_pattern.dat"
`define  candidate_result_Length "./dat/candidate_result_Length.dat"
`define  candidate_united_result_Length "./dat/candidate_united_result_Length.dat"
`define  candidate_diff_result_Length "./dat/candidate_diff_result_Length.dat"
`define  candidate_intersect_result_Length "./dat/candidate_intersect_result_Length.dat"

reg clk = 0;
reg rst;
reg en;
reg [23:0] central;
reg [11:0] radius;
reg [1:0] mode;
wire busy;
wire valid;
wire [7:0] candidate;


integer err_cnt;

reg [23:0] central_pat_mem [0:63];
reg [11:0] radius_pat_mem[0:63];
reg [7:0] expected_mem [0:63];

`ifdef SDFFILE
initial $sdf_annotate(`SDFFILE, u_set);
`endif

initial begin //記得 source  nWave
	$dumpfile("SET_syn.vcd");
	$dumpvars;
end

initial begin
	$timeformat(-9, 1, " ns", 9); //Display time in nanoseconds
	$readmemh(`central_pattern, central_pat_mem);
	$readmemh(`radius_pattern, radius_pat_mem);
`ifdef MD1
	$display("--------------------------- [ Function 1. Simulation START !! ] ---------------------------");
	$readmemh(`candidate_result_Length, expected_mem);
`elsif MD2
	$display("--------------------------- [ Function 2. Simulation START !! ] ---------------------------");
	$readmemh(`candidate_united_result_Length, expected_mem);
`elsif MD3
	$display("--------------------------- [ Function 3. Simulation START !! ] ---------------------------");
	$readmemh(`candidate_diff_result_Length, expected_mem);
`elsif MD4
	$display("--------------------------- [ Function 4. Simulation START !! ] ---------------------------");
	$readmemh(`candidate_intersect_result_Length, expected_mem);
`else
	$display("============================================================================");
	$display("|                                                                          |");
	$display("|  Please select one testbench for test !!                                 |");
	$display("|  Simulation can't be initialized !!                                      |");
	$display("|                                                                          |");
	$display("============================================================================");
	#1 $finish;
`endif
end



always #(`cycle/2) clk = ~clk;



initial begin
`ifdef MD1
	mode = 2'b00;
`elsif MD2
	mode = 2'b01;
`elsif MD3
	mode = 2'b10;
`elsif MD4
	mode = 2'b11;
`else
	mode = 2'bx;
`endif
end

SET u_set( .clk(clk), .rst(rst), .en(en), .central(central), .radius(radius), .mode(mode), .busy(busy), .valid(valid), .candidate(candidate));

integer k;
integer p;
initial begin
	en = 0;
      	rst = 0;
	err_cnt = 0;
# `cycle;     
	rst = 1;
#(`cycle*3);
	rst = 0;
for (k = 0; k<=63; k = k+1) begin
	@(negedge clk);
	//change inputs at strobe point
        #(`cycle/4)	wait(busy == 0);
			en = 1;
			central = central_pat_mem[k];                
      			radius = radius_pat_mem[k];
			#(`cycle) en = 0;
			wait (valid == 1);
          	//Wait for signal output
          	@(negedge clk);
				if (candidate === expected_mem[k])
					$display(" Pattern %d at Mode %d is PASS !", k, mode);
				else begin
					$display(" Pattern %d at Mode %d is FAIL !. Expected candidate = %d, but the Response candidate = %d !! ", k, mode, expected_mem[k], candidate);
					err_cnt = err_cnt + 1;
				end
end
#(`cycle*2); 
     $display("--------------------------- Simulation FINISH !!---------------------------");
     if (err_cnt) begin 
     	$display("============================================================================");
     	$display("\n (T_T) FAIL!! The simulation result is FAIL!!! there were %d errors at all.\n", err_cnt);
	$display("============================================================================");
	end
     else begin 
     	$display("============================================================================");
	$display("\n \\(^o^)/ CONGRATULATIONS!!  The simulation result is PASS!!!\n");
	$display("============================================================================");
	end
$finish;
end


always@(err_cnt) begin
	if (err_cnt == 10) begin
	$display("============================================================================");
     	$display("\n (>_<) FAIL!! The simulation FAIL result is too many ! Please check your code @@ \n");
	$display("============================================================================");
	$finish;
	end
end

initial begin 
	#`terminate_cycle;
	$display("================================================================================================================");
	$display("--------------------------- (/`n`)/ ~#  There was something wrong with your code !! ---------------------------"); 
	$display("--------------------------- The simulation can't finished!!, Please check it !!! ---------------------------"); 
	$display("================================================================================================================");
	$finish;
end


endmodule

SET.vcd
$date
    Jul 13, 2020  15:21:39
$end
$version
    TOOL:	ncsim	15.20-s039
$end
$timescale
    10 ps
$end

$scope module testfixture1 $end
$var reg       1 !    clk  $end
$var reg       1 "    rst  $end
$var reg       1 #    en  $end
$var reg      24 $    central [23:0] $end
$var reg      12 %    radius [11:0] $end
$var reg       2 &    mode [1:0] $end
$var wire      1 '    busy  $end
$var wire      1 (    valid  $end
$var wire      8 )    candidate [7:0] $end
$var integer  32 *    err_cnt  $end
$var integer  32 +    k  $end
$var integer  32 ,    p  $end

$scope module u_set $end
$var wire      1 -    clk  $end
$var wire      1 .    rst  $end
$var wire      1 /    en  $end
$var wire     24 0    central [23:0] $end
$var wire      1 1    radius [11] $end
$var wire      1 2    radius [10] $end
$var wire      1 3    radius [9] $end
$var wire      1 4    radius [8] $end
$var wire      1 5    radius [7] $end
$var wire      1 6    radius [6] $end
$var wire      1 7    radius [5] $end
$var wire      1 8    radius [4] $end
$var wire      1 9    radius [3] $end
$var wire      1 :    radius [2] $end
$var wire      1 ;    radius [1] $end
$var wire      1 <    radius [0] $end
$var wire      1 =    mode [1] $end
$var wire      1 >    mode [0] $end
$var wire      1 '    busy  $end
$var wire      1 (    valid  $end
$var wire      8 )    candidate [7:0] $end
$var reg       2 ?    cs [1:0] $end
$var reg       2 @    ns [1:0] $end
$var reg       8 A    target_ns [7:0] $end
$var reg       8 B    target_cs [7:0] $end
$var reg       8 C    CountIn [7:0] $end
$var wire      1 D    ans_A  $end
$var wire      1 E    ans_B  $end
$var wire      1 F    ans_C  $end
$var wire      4 G    xdiff_A [3:0] $end
$var wire      4 H    xdiff_B [3:0] $end
$var wire      4 I    xdiff_C [3:0] $end
$var wire      4 J    ydiff_A [3:0] $end
$var wire      4 K    ydiff_B [3:0] $end
$var wire      4 L    ydiff_C [3:0] $end
$var wire      8 M    Prod_rA [7:0] $end
$var wire      8 N    Prod_rB [7:0] $end
$var wire      8 O    Prod_rC [7:0] $end
$var wire      8 P    Prod_xdA [7:0] $end
$var wire      8 Q    Prod_xdB [7:0] $end
$var wire      8 R    Prod_xdC [7:0] $end
$var wire      8 S    Prod_ydA [7:0] $end
$var wire      8 T    Prod_ydB [7:0] $end
$var wire      8 U    Prod_ydC [7:0] $end

$scope module M0 $end
$var wire      4 G    A [3:0] $end
$var wire      8 P    Product [7:0] $end
$var wire      8 V    temp0 [7:0] $end
$var wire      8 W    temp1 [7:0] $end
$var wire      8 X    temp2 [7:0] $end
$upscope $end


$scope module M1 $end
$var wire      4 J    A [3:0] $end
$var wire      8 S    Product [7:0] $end
$var wire      8 Y    temp0 [7:0] $end
$var wire      8 Z    temp1 [7:0] $end
$var wire      8 [    temp2 [7:0] $end
$upscope $end


$scope module M2 $end
$var wire      4 H    A [3:0] $end
$var wire      8 Q    Product [7:0] $end
$var wire      8 \    temp0 [7:0] $end
$var wire      8 ]    temp1 [7:0] $end
$var wire      8 ^    temp2 [7:0] $end
$upscope $end


$scope module M3 $end
$var wire      4 K    A [3:0] $end
$var wire      8 T    Product [7:0] $end
$var wire      8 _    temp0 [7:0] $end
$var wire      8 `    temp1 [7:0] $end
$var wire      8 a    temp2 [7:0] $end
$upscope $end


$scope module M4 $end
$var wire      4 I    A [3:0] $end
$var wire      8 R    Product [7:0] $end
$var wire      8 b    temp0 [7:0] $end
$var wire      8 c    temp1 [7:0] $end
$var wire      8 d    temp2 [7:0] $end
$upscope $end


$scope module M5 $end
$var wire      4 L    A [3:0] $end
$var wire      8 U    Product [7:0] $end
$var wire      8 e    temp0 [7:0] $end
$var wire      8 f    temp1 [7:0] $end
$var wire      8 g    temp2 [7:0] $end
$upscope $end


$scope module M6 $end
$var wire      1 1    A [3] $end
$var wire      1 2    A [2] $end
$var wire      1 3    A [1] $end
$var wire      1 4    A [0] $end
$var wire      8 M    Product [7:0] $end
$var wire      8 h    temp0 [7:0] $end
$var wire      8 i    temp1 [7:0] $end
$var wire      8 j    temp2 [7:0] $end
$upscope $end


$scope module M7 $end
$var wire      1 5    A [3] $end
$var wire      1 6    A [2] $end
$var wire      1 7    A [1] $end
$var wire      1 8    A [0] $end
$var wire      8 N    Product [7:0] $end
$var wire      8 k    temp0 [7:0] $end
$var wire      8 l    temp1 [7:0] $end
$var wire      8 m    temp2 [7:0] $end
$upscope $end


$scope module M8 $end
$var wire      1 9    A [3] $end
$var wire      1 :    A [2] $end
$var wire      1 ;    A [1] $end
$var wire      1 <    A [0] $end
$var wire      8 O    Product [7:0] $end
$var wire      8 n    temp0 [7:0] $end
$var wire      8 o    temp1 [7:0] $end
$var wire      8 p    temp2 [7:0] $end
$upscope $end


$scope module JA $end
$var wire      8 P    square_x [7:0] $end
$var wire      8 S    square_y [7:0] $end
$var wire      8 M    square_r [7:0] $end
$var wire      1 D    ans  $end
$var wire      8 q    diff_square [7:0] $end
$upscope $end


$scope module JB $end
$var wire      8 Q    square_x [7:0] $end
$var wire      8 T    square_y [7:0] $end
$var wire      8 N    square_r [7:0] $end
$var wire      1 E    ans  $end
$var wire      8 r    diff_square [7:0] $end
$upscope $end


$scope module JC $end
$var wire      8 R    square_x [7:0] $end
$var wire      8 U    square_y [7:0] $end
$var wire      8 O    square_r [7:0] $end
$var wire      1 F    ans  $end
$var wire      8 s    diff_square [7:0] $end
$upscope $end


$scope module C0 $end
$var wire      1 D    A  $end
$var wire      1 E    B  $end
$var wire      1 F    C  $end
$var wire      1 =    mode [1] $end
$var wire      1 >    mode [0] $end
$var wire      1 t    state [1] $end
$var wire      1 u    state [0] $end
$var wire      8 v    CountIn [7:0] $end
$var wire      8 )    CountOut [7:0] $end
$var wire      1 w    m0  $end
$var wire      1 x    m1  $end
$var wire      1 y    m2  $end
$var wire      1 z    m3  $end
$var wire      1 {    w0  $end
$var wire      1 |    w1  $end
$var wire      1 }    w2  $end
$var wire      1 ~    w3  $end
$upscope $end

$upscope $end

$upscope $end

$enddefinitions $end
$dumpvars
0!
0"
0#
bx $
bx %
b11 &
x'
x(
bx )
b0 *
bx +
bx ,
0-
0.
0/
bx 0
x1
x2
x3
x4
x5
x6
x7
x8
x9
x:
x;
x<
1=
1>
bx ?
bx @
bx A
bx B
bx C
xD
xE
xF
bx G
bx H
bx I
bx J
bx K
bx L
b0xxxxxxx M
b0xxxxxxx N
b0xxxxxxx O
b0xxxxxxx P
b0xxxxxxx Q
b0xxxxxxx R
b0xxxxxxx S
b0xxxxxxx T
b0xxxxxxx U
b0xxxxxxx V
b0xxxxxxx W
b0xxxxxxx X
b0xxxxxxx Y
b0xxxxxxx Z
b0xxxxxxx [
b0xxxxxxx \
b0xxxxxxx ]
b0xxxxxxx ^
b0xxxxxxx _
b0xxxxxxx `
b0xxxxxxx a
b0xxxxxxx b
b0xxxxxxx c
b0xxxxxxx d
b0xxxxxxx e
b0xxxxxxx f
b0xxxxxxx g
b0xxxxxxx h
b0xxxxxxx i
b0xxxxxxx j
b0xxxxxxx k
b0xxxxxxx l
b0xxxxxxx m
b0xxxxxxx n
b0xxxxxxx o
b0xxxxxxx p
bx q
bx r
bx s
xt
xu
bx v
0w
0x
0y
xz
x{
x|
x}
x~
$end
#500
1!
1-
#1000
1"
0!
0-
1.
b0 ?
b10000 B
b0 C
0t
0u
0'
0(
b0 v
0~
b0 )
b0 @
b10001 A
#1500
1!
1-
#2000
0!
0-
#2500
1!
1-
#3000
0!
0-
#3500
1!
1-
#4000
0"
b0 +
0!
0-
0.
#4250
1#
b10101010011001101100010 $
b1100110010 %
01
02
13
14
05
06
17
18
09
0:
1;
0<
b10101010011001101100010 0
1/
b10 L
b101 I
b11 K
b10 H
b101 J
b100 G
b1 n
b11001 k
b11001 h
b100100 i
b100100 l
b10000 o
b10 V
b101010 Y
b1 \
b11001 _
b101010 b
b1 e
b10000 f
b10101 c
b100100 `
b10000 ]
b10101 Z
b1 W
b1000 p
b10010 m
b10010 j
b1001 M
b1001 N
b100 O
b100000 X
b110010 [
b1000 ^
b10010 a
b110010 d
b1000 g
b100 U
b11001 R
b1001 T
b100 Q
b11001 S
b10000 P
b11100000 q
b11111100 r
b11100111 s
0F
0E
0D
0{
0}
1|
0z
b1 @
#4500
1!
1-
b1 ?
b10001 B
b1 L
b10 K
b100 J
1u
1'
1~
b10 Y
b101010 [
b1 _
b11100 `
b1000 e
b1000 f
b100 g
b100 f
b1110 a
b10000 `
b10101 S
b1 Z
b100000 [
b11100100 q
b1000 a
b111 T
b10 g
b10 U
b11101001 s
b1 U
b11111110 r
b100 T
b10000 S
b11101001 q
b1 r
b11101010 s
1E
1{
1}
0|
b10010 A
#5000
0!
0-
#5250
0#
0/
#5500
1!
1-
b10010 B
b0 L
b1 K
b11 J
b11001 Y
b11000 [
b1000 _
b1000 `
b0 e
b0 f
b100 a
b100 `
b1100 S
b100100 Z
b10010 [
b11101101 q
b10 a
b10 T
b0 g
b0 U
b11 r
b1 T
b1001 S
b11110000 q
b100 r
b11101011 s
b10011 A
#6000
0!
0-
#6500
1!
1-
b10011 B
b1 L
b0 K
b10 J
b1 Y
b11100 Z
b0 _
b1000 e
b100 f
b0 `
b1110 [
b10000 Z
b1000 [
b111 S
b0 a
b10 g
b1 U
b0 T
b11110010 q
b100 S
b11110101 q
b101 r
b11101010 s
b10100 A
#7000
0!
0-
#7500
1!
1-
b10100 B
b10 L
b1 K
b1 J
b1000 Y
b1000 Z
b1000 _
b1 e
b10000 f
b100 `
b100 [
b100 Z
b10 [
b10 S
b10 a
b1000 g
b100 U
b1 T
b11110111 q
b1 S
b11111000 q
b100 r
b11100111 s
b10101 A
#8000
0!
0-
#8500
1!
1-
b10101 B
b11 L
b10 K
b0 J
b0 Y
b1 _
b11001 e
b11000 f
b1100 g
b100100 f
b10000 `
b0 Z
b0 [
b1000 a
b10010 g
b110 U
b11100101 s
b1001 U
b100 T
b0 S
b11111001 q
b1 r
b11100010 s
b10110 A
#9000
0!
0-
#9500
1!
1-
b10110 B
b100 L
b11 K
b1 J
b1000 Y
b11001 _
b11000 `
b10 e
b101100 f
b10110 g
b1 f
b1100 a
b100100 `
b100 Z
b10 [
b10010 a
b110 T
b100000 g
b1011 U
b11100000 s
b10000 U
b11111111 r
b1001 T
b1 S
b11111000 q
b11111100 r
0E
b11011011 s
0{
0}
1|
b10111 A
#10000
0!
0-
#10500
1!
1-
b10111 B
b101 L
b100 K
b10 J
b1 Y
b10 _
b101100 `
b101010 e
b101000 g
b10100 U
b10101 f
b10110 a
b1 `
b10000 Z
b1000 [
b100000 a
b1011 T
b110010 g
b11010111 s
b11001 U
b11111010 r
b10000 T
b100 S
b11110101 q
b11110101 r
b11010010 s
b11000 A
#11000
0!
0-
#11500
1!
1-
b11000 B
b110 L
b101 K
b11 J
b11001 Y
b11000 Z
b101010 _
b101000 a
b11 e
b111010 g
b11101 U
b110001 f
b10100 T
b10101 `
b1100 [
b100100 Z
b10010 [
b110 S
b110010 a
b11110001 r
b1001000 g
b11001110 s
b100100 U
b11001 T
b11110011 q
b1001 S
b11110000 q
b11101100 r
b11000111 s
b100001 A
#12000
0!
0-
#12500
1!
1-
b100001 B
b1 L
b100 I
b10 K
b1 H
b100 J
b11 G
b11001 V
b11000 X
b10 Y
b101100 Z
b1000 \
b1000 ]
b1 _
b11010 a
b10 b
b101010 d
b1000 e
b1001 f
b100000 g
b10000 U
b1100 g
b100 f
b10101 R
b1 c
b1101 T
b10000 `
b100 ^
b100 ]
b10110 [
b1 Z
b1100 P
b100100 W
b10010 X
b11110100 q
b100000 [
b1011 S
b10 ^
b10 Q
b1000 a
b11111000 r
b100000 d
b10 g
b110 U
b11011111 s
b11101001 s
b1 U
b10000 R
b100 T
b11111010 r
b1 Q
b11110010 q
b10000 S
b1001 P
b11110000 q
b100 r
b11110011 s
1E
1{
1}
0|
b100010 A
#13000
0!
0-
#13500
1!
1-
b100010 B
b0 L
b1 K
b11 J
b11001 Y
b11000 [
b1000 _
b1000 `
b0 e
b0 f
b100 a
b100 `
b1100 S
b100100 Z
b10010 [
b11110100 q
b10 a
b10 T
b0 g
b0 U
b110 r
b1 T
b1001 S
b11110111 q
b111 r
b11110100 s
b100011 A
#14000
0!
0-
#14500
1!
1-
b100011 B
b1 L
b0 K
b10 J
b1 Y
b11100 Z
b0 _
b1000 e
b100 f
b0 `
b1110 [
b10000 Z
b1000 [
b111 S
b0 a
b10 g
b1 U
b0 T
b11111001 q
b100 S
b11111100 q
b1000 r
b11110011 s
b100100 A
#15000
0!
0-
#15500
1!
1-
b100100 B
b10 L
b1 K
b1 J
b1000 Y
b1000 Z
b1000 _
b1 e
b10000 f
b100 `
b100 [
b100 Z
b10 [
b10 S
b10 a
b1000 g
b100 U
b1 T
b11111110 q
b1 S
b11111111 q
b111 r
b11110000 s
b100101 A
#16000
0!
0-
#16500
1!
1-
b100101 B
b11 L
b10 K
b0 J
b0 Y
b1 _
b11001 e
b11000 f
b1100 g
b100100 f
b10000 `
b0 Z
b0 [
b1000 a
b10010 g
b110 U
b11101110 s
b1001 U
b100 T
b0 S
b0 q
b100 r
b11101011 s
1D
0{
1|
1z
b1 )
b100110 A
#17000
0!
0-
#17500
1!
1-
b100110 B
b1 C
b100 L
b11 K
b1 J
b1 v
b10 )
b1000 Y
b11001 _
b11000 `
b10 e
b101100 f
b10110 g
b1 f
b1100 a
b100100 `
b100 Z
b10 [
b10010 a
b110 T
b100000 g
b1011 U
b11101001 s
b10000 U
b10 r
b1001 T
b1 S
b11111111 q
b11111111 r
b11100100 s
0E
0D
0}
0z
b1 )
b100111 A
#18000
0!
0-
#18500
1!
1-
b100111 B
b101 L
b100 K
b10 J
b1 Y
b10 _
b101100 `
b101010 e
b101000 g
b10100 U
b10101 f
b10110 a
b1 `
b10000 Z
b1000 [
b100000 a
b1011 T
b110010 g
b11100000 s
b11001 U
b11111101 r
b10000 T
b100 S
b11111100 q
b11111000 r
b11011011 s
b101000 A
#19000
0!
0-
#19500
1!
1-
b101000 B
b110 L
b101 K
b11 J
b11001 Y
b11000 Z
b101010 _
b101000 a
b11 e
b111010 g
b11101 U
b110001 f
b10100 T
b10101 `
b1100 [
b100100 Z
b10010 [
b110 S
b110010 a
b11110100 r
b1001000 g
b11010111 s
b100100 U
b11001 T
b11111010 q
b1001 S
b11110111 q
b11101111 r
b11010000 s
b110001 A
#20000
0!
0-
#20500
1!
1-
b110001 B
b1 L
b11 I
b10 K
b0 H
b100 J
b10 G
b1 V
b11100 W
b10 Y
b101100 Z
b0 \
b1 _
b11010 a
b11001 b
b11000 d
b1000 e
b1001 f
b100000 g
b10000 U
b1100 g
b100 f
b1100 R
b100100 c
b1101 T
b10000 `
b0 ]
b10110 [
b1 Z
b1110 X
b10000 W
b1000 X
b111 P
b100000 [
b1011 S
b0 ^
b1000 a
b11111011 r
b10010 d
b10 g
b110 U
b11101000 s
b11110010 s
b1 U
b1001 R
b100 T
b0 Q
b10000 S
b100 P
b11110101 q
b101 r
b11111010 s
1E
1{
1}
0|
b110010 A
#21000
0!
0-
#21500
1!
1-
b110010 B
b0 L
b1 K
b11 J
b11001 Y
b11000 [
b1000 _
b1000 `
b0 e
b0 f
b100 a
b100 `
b1100 S
b100100 Z
b10010 [
b11111001 q
b10 a
b10 T
b0 g
b0 U
b111 r
b1 T
b1001 S
b11111100 q
b1000 r
b11111011 s
b110011 A
#22000
0!
0-
#22500
1!
1-
b110011 B
b1 L
b0 K
b10 J
b1 Y
b11100 Z
b0 _
b1000 e
b100 f
b0 `
b1110 [
b10000 Z
b1000 [
b111 S
b0 a
b10 g
b1 U
b0 T
b11111110 q
b100 S
b1 q
b1001 r
b11111010 s
1D
0{
1|
1z
b10 )
b110100 A
#23000
0!
0-
#23500
1!
1-
b110100 B
b10 C
b10 L
b1 K
b1 J
b10 v
b11 )
b1000 Y
b1000 Z
b1000 _
b1 e
b10000 f
b100 `
b100 [
b100 Z
b10 [
b10 S
b10 a
b1000 g
b100 U
b1 T
b11 q
b1 S
b100 q
b1000 r
b11110111 s
b110101 A
#24000
0!
0-
#24500
1!
1-
b110101 B
b11 C
b11 L
b10 K
b0 J
b11 v
b100 )
b0 Y
b1 _
b11001 e
b11000 f
b1100 g
b100100 f
b10000 `
b0 Z
b0 [
b1000 a
b10010 g
b110 U
b11110101 s
b1001 U
b100 T
b0 S
b101 q
b101 r
b11110010 s
b110110 A
#25000
0!
0-
#25500
1!
1-
b110110 B
b100 C
b100 L
b11 K
b1 J
b100 v
b101 )
b1000 Y
b11001 _
b11000 `
b10 e
b101100 f
b10110 g
b1 f
b1100 a
b100100 `
b100 Z
b10 [
b10010 a
b110 T
b100000 g
b1011 U
b11110000 s
b10000 U
b11 r
b1001 T
b1 S
b100 q
b0 r
b11101011 s
b110111 A
#26000
0!
0-
#26500
1!
1-
b110111 B
b101 C
b101 L
b100 K
b10 J
b101 v
b110 )
b1 Y
b10 _
b101100 `
b101010 e
b101000 g
b10100 U
b10101 f
b10110 a
b1 `
b10000 Z
b1000 [
b100000 a
b1011 T
b110010 g
b11100111 s
b11001 U
b11111110 r
b10000 T
b100 S
b1 q
b11111001 r
0E
b11100010 s
1{
0|
0z
b101 )
b111000 A
#27000
0!
0-
#27500
1!
1-
b111000 B
b110 L
b101 K
b11 J
b11001 Y
b11000 Z
b101010 _
b101000 a
b11 e
b111010 g
b11101 U
b110001 f
b10100 T
b10101 `
b1100 [
b100100 Z
b10010 [
b110 S
b110010 a
b11110101 r
b1001000 g
b11011110 s
b100100 U
b11001 T
b11111111 q
b1001 S
b11111100 q
0D
b11110000 r
b11010111 s
0{
0}
1|
b1000001 A
#28000
0!
0-
#28500
1!
1-
b1000001 B
b1 L
b10 I
b10 K
b1 H
b100 J
b1 G
b1000 V
b1000 W
b10 Y
b101100 Z
b1000 \
b1 _
b11010 a
b1 b
b11100 c
b1000 e
b1001 f
b100000 g
b10000 U
b1100 g
b100 f
b1110 d
b10000 c
b1101 T
b10000 `
b100 ]
b10110 [
b1 Z
b100 X
b100 W
b10 X
b10 P
b100000 [
b1011 S
b10 ^
b1000 a
b11111100 r
b1000 d
b111 R
b10 g
b110 U
b11101011 s
b1 U
b11110111 s
b100 R
b100 T
b1 Q
b10000 S
b1 P
b11111000 q
b100 r
b11111111 s
1E
1{
1}
0|
b1000010 A
#29000
0!
0-
#29500
1!
1-
b1000010 B
b0 L
b1 K
b11 J
b11001 Y
b11000 [
b1000 _
b1000 `
b0 e
b0 f
b100 a
b100 `
b1100 S
b100100 Z
b10010 [
b11111100 q
b10 a
b10 T
b0 g
b0 U
b110 r
b1 T
b1001 S
b11111111 q
b111 r
b0 s
1F
1|
1z
b110 )
b1000011 A
#30000
0!
0-
#30500
1!
1-
b1000011 B
b110 C
b1 L
b0 K
b10 J
b110 v
b111 )
b1 Y
b11100 Z
b0 _
b1000 e
b100 f
b0 `
b1110 [
b10000 Z
b1000 [
b111 S
b0 a
b10 g
b1 U
b0 T
b1 q
b100 S
b100 q
1D
b1000 r
b11111111 s
0{
0|
0z
b110 )
0F
1|
1z
b111 )
b1000100 A
#31000
0!
0-
#31500
1!
1-
b1000100 B
b111 C
b10 L
b1 K
b1 J
b111 v
b1000 )
b1000 Y
b1000 Z
b1000 _
b1 e
b10000 f
b100 `
b100 [
b100 Z
b10 [
b10 S
b10 a
b1000 g
b100 U
b1 T
b110 q
b1 S
b111 q
b111 r
b11111100 s
b1000101 A
#32000
0!
0-
#32500
1!
1-
b1000101 B
b1000 C
b11 L
b10 K
b0 J
b1000 v
b1001 )
b0 Y
b1 _
b11001 e
b11000 f
b1100 g
b100100 f
b10000 `
b0 Z
b0 [
b1000 a
b10010 g
b110 U
b11111010 s
b1001 U
b100 T
b0 S
b1000 q
b100 r
b11110111 s
b1000110 A
#33000
0!
0-
#33500
1!
1-
b1000110 B
b1001 C
b100 L
b11 K
b1 J
b1001 v
b1010 )
b1000 Y
b11001 _
b11000 `
b10 e
b101100 f
b10110 g
b1 f
b1100 a
b100100 `
b100 Z
b10 [
b10010 a
b110 T
b100000 g
b1011 U
b11110101 s
b10000 U
b10 r
b1001 T
b1 S
b111 q
b11111111 r
b11110000 s
0E
1{
0|
0z
b1001 )
b1000111 A
#34000
0!
0-
#34500
1!
1-
b1000111 B
b101 L
b100 K
b10 J
b1 Y
b10 _
b101100 `
b101010 e
b101000 g
b10100 U
b10101 f
b10110 a
b1 `
b10000 Z
b1000 [
b100000 a
b1011 T
b110010 g
b11101100 s
b11001 U
b11111101 r
b10000 T
b100 S
b100 q
b11111000 r
b11100111 s
b1001000 A
#35000
0!
0-
